[{"spaceid":"VS336","blockface":"4900 SUNSET BL","metertype":"Single-Space","ratetype":"FLAT","raterange":"$1.00","timelimit":"2HR","parkingpolicy":"TANS 4P-7P Mon-Fri | PKG 8A-4P Mon-Fri, 8A-8P Sat","latlng":{"latitude":"34.098024","longitude":"-118.296664"},":@computed_region_qz3q_ghft":"23445",":@computed_region_k96s_3jcv":"430",":@computed_region_tatf_ua23":"456",":@computed_region_ur2y_g4cx":"16",":@computed_region_kqwf_mjcx":"8",":@computed_region_2dna_qi2s":"58"}
,{"spaceid":"ED396","blockface":"700 E PICO BLVD","metertype":"Single-Space","ratetype":"TOD","raterange":"$0.5 - $1","timelimit":"2HR","parkingpolicy":"8A-6P Mon-Sat","latlng":{"latitude":"34.032054","longitude":"-118.252521"},":@computed_region_qz3q_ghft":"23082",":@computed_region_k96s_3jcv":"703",":@computed_region_tatf_ua23":"1018",":@computed_region_kqwf_mjcx":"9",":@computed_region_2dna_qi2s":"76"}
,{"spaceid":"CB211A","blockface":"1300 S GRAND AVE","metertype":"Single-Space","ratetype":"FLAT","raterange":"$0.50","timelimit":"4HR","parkingpolicy":"8A-8P Mon-Sat","latlng":{"latitude":"34.038125","longitude":"-118.264675"},":@computed_region_qz3q_ghft":"23076",":@computed_region_k96s_3jcv":"693",":@computed_region_tatf_ua23":"1291",":@computed_region_kqwf_mjcx":"9",":@computed_region_2dna_qi2s":"76"}]